scrapinsta/__init__.py
scrapinsta/scrapinsta.py
scrapinsta-0.0.2.dist-info/LICENSE
scrapinsta-0.0.2.dist-info/METADATA
scrapinsta-0.0.2.dist-info/WHEEL
scrapinsta-0.0.2.dist-info/top_level.txt
scrapinsta-0.0.2.dist-info/RECORD
