Metadata-Version: 2.1
Name: scrapinsta
Version: 0.0.2
Summary: A package to scraping data from Instagram
Home-page: https://github.com/matheuskolln/scrapinsta
Author: Matheus Kolln
Author-email: matheuzhenrik@gmail.com
License: UNKNOWN
Platform: UNKNOWN
Classifier: Programming Language :: Python :: 3
Classifier: License :: OSI Approved :: MIT License
Classifier: Operating System :: OS Independent
Requires-Python: >=3.6
